cellar_extractor/__init__.py
cellar_extractor/cellar.py
cellar_extractor/cellar_extra_extract.py
cellar_extractor/cellar_queries.py
cellar_extractor/cellar_sparql_queries.py
cellar_extractor/citations_adder.py
cellar_extractor/csv_extractor.py
cellar_extractor/eurlex_scraping.py
cellar_extractor/fulltext_saving.py
cellar_extractor/json_to_csv.py
cellar_extractor/nodes_and_edges.py
cellar_extractor/operative_extractions.py
cellar_extractor/sparql.py
cellar_extractor-1.2.4.dist-info/licenses/LICENSE
cellar_extractor-1.2.4.dist-info/METADATA
cellar_extractor-1.2.4.dist-info/WHEEL
cellar_extractor-1.2.4.dist-info/top_level.txt
cellar_extractor-1.2.4.dist-info/RECORD
