Metadata-Version: 2.4
Name: cellar-extractor
Version: 1.2.4
Summary: Library for extracting CELLAR case law data from EUR-Lex
Author-email: LawTech Lab <law-techlab@maastrichtuniversity.nl>
License: Apache-2.0
Project-URL: Homepage, https://github.com/maastrichtlawtech/cellar-extractor
Project-URL: Bug Tracker, https://github.com/maastrichtlawtech/cellar-extractor/issues
Project-URL: Documentation, https://github.com/maastrichtlawtech/cellar-extractor/blob/main/README.md
Project-URL: Source Code, https://github.com/maastrichtlawtech/cellar-extractor
Keywords: cellar,extractor,eurlex,legal,case-law,sparql,ecli
Classifier: Development Status :: 4 - Beta
Classifier: Intended Audience :: Developers
Classifier: Intended Audience :: Legal Industry
Classifier: Intended Audience :: Science/Research
Classifier: Operating System :: OS Independent
Classifier: Programming Language :: Python :: 3
Classifier: Programming Language :: Python :: 3.9
Classifier: Programming Language :: Python :: 3.10
Classifier: Programming Language :: Python :: 3.11
Classifier: Programming Language :: Python :: 3.12
Classifier: Topic :: Scientific/Engineering :: Information Analysis
Classifier: Topic :: Text Processing :: Linguistic
Requires-Python: >=3.9
License-File: LICENSE
Requires-Dist: beautifulsoup4
Requires-Dist: SPARQLWrapper
Requires-Dist: requests
Requires-Dist: pandas
Requires-Dist: xmltodict
Requires-Dist: tqdm
Dynamic: license-file
